{
  "model_type": "prophet",
  "training_completed": "2026-01-25T02:48:33.251458",
  "stocks_trained": 0,
  "stocks_failed": 0,
  "skipped": true,
  "skip_reason": "Prophet incompatible with pandas 3.0.0",
  "average_metrics": {
    "mse": null,
    "mae": null,
    "mape": null,
    "directional_accuracy": null
  },
  "config": {
    "yearly_seasonality": true,
    "weekly_seasonality": true,
    "daily_seasonality": false,
    "changepoint_prior_scale": 0.05,
    "forecast_days": 30
  },
  "stock_results": []
}